setup.py
login_forex_next3/__init__.py
login_forex_next3/login_forex_next3.py
login_forex_next3.egg-info/PKG-INFO
login_forex_next3.egg-info/SOURCES.txt
login_forex_next3.egg-info/dependency_links.txt
login_forex_next3.egg-info/not-zip-safe
login_forex_next3.egg-info/top_level.txt