Metadata-Version: 1.0
Name: login-forex-next3
Version: 1.3
Summary: login_forex_next3
Home-page: UNKNOWN
Author: omid
Author-email: UNKNOWN
License: UNKNOWN
Platform: UNKNOWN
